pipecat_murf_tts/__init__.py
pipecat_murf_tts/tts.py
pipecat_murf_tts-0.1.4.dist-info/METADATA
pipecat_murf_tts-0.1.4.dist-info/WHEEL
pipecat_murf_tts-0.1.4.dist-info/licenses/LICENSE
pipecat_murf_tts-0.1.4.dist-info/RECORD
