Metadata-Version: 2.4
Name: pipecat-murf-tts
Version: 0.1.4
Summary: Official Murf TTS integration for Pipecat
Project-URL: Repository, https://github.com/murf-ai/pipecat-murf-tts
Project-URL: Issues, https://github.com/murf-ai/pipecat-murf-tts/issues
Author-email: Nilesh Inkane <nilesh.inkane@murf.ai>
License-Expression: MIT
License-File: LICENSE
Requires-Python: <3.13,>=3.10
Requires-Dist: loguru>=0.7.3
Requires-Dist: pipecat-ai<0.1.0,>=0.0.97
Requires-Dist: python-dotenv>=1.1.1
Requires-Dist: websockets<16.0,>=15.0.1
